{"120":{"50":{"t":"grass","e":null},"51":{"t":"grass","e":null},"52":{"t":"grass","e":null},"53":{"t":"grass","e":null},"54":{"t":"grass","e":null},"55":{"t":"grass","e":null},"56":{"t":"grass","e":null},"57":{"t":"grass","e":null},"58":{"t":"grass","e":null},"59":{"t":"grass","e":null}},"121":{"50":{"t":"grass","e":null},"51":{"t":"grass","e":null},"52":{"t":"grass","e":null},"53":{"t":"grass","e":null},"54":{"t":"grass","e":null},"55":{"t":"grass","e":null},"56":{"t":"grass","e":null},"57":{"t":"grass","e":null},"58":{"t":"grass","e":null},"59":{"t":"grass","e":null}},"122":{"50":{"t":"grass","e":null},"51":{"t":"grass","e":null},"52":{"t":"grass","e":null},"53":{"t":"grass","e":null},"54":{"t":"grass","e":null},"55":{"t":"grass","e":null},"56":{"t":"grass","e":null},"57":{"t":"water","e":null},"58":{"t":"grass","e":null},"59":{"t":"grass","e":null}},"123":{"50":{"t":"grass","e":null},"51":{"t":"grass","e":null},"52":{"t":"grass","e":null},"53":{"t":"grass","e":null},"54":{"t":"grass","e":null},"55":{"t":"grass","e":null},"56":{"t":"grass","e":null},"57":{"t":"water","e":null},"58":{"t":"water","e":null},"59":{"t":"grass","e":null}},"124":{"50":{"t":"grass","e":null},"51":{"t":"grass","e":null},"52":{"t":"grass","e":null},"53":{"t":"grass","e":null},"54":{"t":"grass","e":null},"55":{"t":"grass","e":null},"56":{"t":"grass","e":null},"57":{"t":"grass","e":null},"58":{"t":"grass","e":null},"59":{"t":"grass","e":null}},"125":{"50":{"t":"grass","e":null},"51":{"t":"grass","e":null},"52":{"t":"grass","e":null},"53":{"t":"grass","e":null},"54":{"t":"grass","e":null},"55":{"t":"grass","e":null},"56":{"t":"grass","e":null},"57":{"t":"grass","e":null},"58":{"t":"grass","e":null},"59":{"t":"dirt","e":null}},"126":{"50":{"t":"grass","e":null},"51":{"t":"grass","e":null},"52":{"t":"grass","e":null},"53":{"t":"grass","e":null},"54":{"t":"grass","e":null},"55":{"t":"grass","e":null},"56":{"t":"grass","e":null},"57":{"t":"grass","e":null},"58":{"t":"grass","e":null},"59":{"t":"dirt","e":"paper"}},"127":{"50":{"t":"grass","e":null},"51":{"t":"grass","e":null},"52":{"t":"grass","e":null},"53":{"t":"grass","e":null},"54":{"t":"grass","e":null},"55":{"t":"grass","e":null},"56":{"t":"grass","e":null},"57":{"t":"grass","e":null},"58":{"t":"grass","e":null},"59":{"t":"dirt","e":null}},"128":{"50":{"t":"grass","e":null},"51":{"t":"grass","e":null},"52":{"t":"grass","e":null},"53":{"t":"grass","e":null},"54":{"t":"grass","e":null},"55":{"t":"grass","e":null},"56":{"t":"grass","e":null},"57":{"t":"grass","e":null},"58":{"t":"grass","e":null},"59":{"t":"dirt","e":null}},"129":{"50":{"t":"grass","e":null},"51":{"t":"grass","e":null},"52":{"t":"grass","e":null},"53":{"t":"grass","e":null},"54":{"t":"grass","e":null},"55":{"t":"grass","e":null},"56":{"t":"grass","e":null},"57":{"t":"grass","e":null},"58":{"t":"grass","e":null},"59":{"t":"dirt","e":null}}}