{"50":{"30":{"t":"dirt","e":null},"31":{"t":"grass","e":null},"32":{"t":"grass","e":null},"33":{"t":"grass","e":null},"34":{"t":"grass","e":null},"35":{"t":"grass","e":"bottle"},"36":{"t":"grass","e":null},"37":{"t":"grass","e":null},"38":{"t":"grass","e":null},"39":{"t":"grass","e":null}},"51":{"30":{"t":"grass","e":null},"31":{"t":"grass","e":null},"32":{"t":"grass","e":null},"33":{"t":"grass","e":null},"34":{"t":"grass","e":null},"35":{"t":"grass","e":null},"36":{"t":"grass","e":null},"37":{"t":"grass","e":null},"38":{"t":"grass","e":null},"39":{"t":"grass","e":null}},"52":{"30":{"t":"grass","e":null},"31":{"t":"grass","e":null},"32":{"t":"grass","e":null},"33":{"t":"grass","e":null},"34":{"t":"grass","e":null},"35":{"t":"grass","e":null},"36":{"t":"grass","e":null},"37":{"t":"grass","e":null},"38":{"t":"grass","e":null},"39":{"t":"grass","e":null}},"53":{"30":{"t":"grass","e":null},"31":{"t":"grass","e":null},"32":{"t":"grass","e":null},"33":{"t":"grass","e":null},"34":{"t":"grass","e":null},"35":{"t":"grass","e":null},"36":{"t":"grass","e":null},"37":{"t":"grass","e":null},"38":{"t":"grass","e":null},"39":{"t":"grass","e":null}},"54":{"30":{"t":"grass","e":null},"31":{"t":"grass","e":null},"32":{"t":"grass","e":null},"33":{"t":"grass","e":null},"34":{"t":"grass","e":null},"35":{"t":"grass","e":null},"36":{"t":"grass","e":null},"37":{"t":"grass","e":null},"38":{"t":"grass","e":null},"39":{"t":"grass","e":null}},"55":{"30":{"t":"grass","e":null},"31":{"t":"grass","e":null},"32":{"t":"grass","e":null},"33":{"t":"grass","e":null},"34":{"t":"grass","e":null},"35":{"t":"grass","e":null},"36":{"t":"grass","e":null},"37":{"t":"grass","e":null},"38":{"t":"grass","e":null},"39":{"t":"grass","e":null}},"56":{"30":{"t":"grass","e":null},"31":{"t":"grass","e":null},"32":{"t":"grass","e":null},"33":{"t":"grass","e":null},"34":{"t":"grass","e":null},"35":{"t":"grass","e":null},"36":{"t":"grass","e":null},"37":{"t":"grass","e":null},"38":{"t":"grass","e":null},"39":{"t":"grass","e":null}},"57":{"30":{"t":"grass","e":"bottle"},"31":{"t":"grass","e":null},"32":{"t":"grass","e":null},"33":{"t":"grass","e":null},"34":{"t":"grass","e":null},"35":{"t":"grass","e":null},"36":{"t":"grass","e":null},"37":{"t":"grass","e":null},"38":{"t":"grass","e":null},"39":{"t":"grass","e":null}},"58":{"30":{"t":"dirt","e":null},"31":{"t":"dirt","e":null},"32":{"t":"grass","e":null},"33":{"t":"grass","e":null},"34":{"t":"grass","e":null},"35":{"t":"grass","e":null},"36":{"t":"grass","e":null},"37":{"t":"grass","e":null},"38":{"t":"grass","e":null},"39":{"t":"grass","e":"bottle"}},"59":{"30":{"t":"dirt","e":null},"31":{"t":"dirt","e":null},"32":{"t":"grass","e":null},"33":{"t":"grass","e":null},"34":{"t":"grass","e":null},"35":{"t":"grass","e":null},"36":{"t":"grass","e":null},"37":{"t":"grass","e":null},"38":{"t":"grass","e":null},"39":{"t":"grass","e":null}}}