{"60":{"140":{"t":"grass","e":null},"141":{"t":"grass","e":null},"142":{"t":"grass","e":null},"143":{"t":"grass","e":null},"144":{"t":"grass","e":null},"145":{"t":"grass","e":null},"146":{"t":"grass","e":null},"147":{"t":"grass","e":null},"148":{"t":"grass","e":null},"149":{"t":"grass","e":null}},"61":{"140":{"t":"grass","e":null},"141":{"t":"grass","e":null},"142":{"t":"grass","e":null},"143":{"t":"grass","e":null},"144":{"t":"grass","e":null},"145":{"t":"grass","e":null},"146":{"t":"grass","e":null},"147":{"t":"grass","e":null},"148":{"t":"grass","e":null},"149":{"t":"grass","e":null}},"62":{"140":{"t":"grass","e":null},"141":{"t":"grass","e":null},"142":{"t":"grass","e":null},"143":{"t":"grass","e":null},"144":{"t":"grass","e":null},"145":{"t":"grass","e":null},"146":{"t":"grass","e":null},"147":{"t":"grass","e":null},"148":{"t":"grass","e":null},"149":{"t":"grass","e":null}},"63":{"140":{"t":"grass","e":null},"141":{"t":"grass","e":null},"142":{"t":"grass","e":null},"143":{"t":"grass","e":null},"144":{"t":"grass","e":null},"145":{"t":"grass","e":null},"146":{"t":"grass","e":null},"147":{"t":"dirt","e":null},"148":{"t":"dirt","e":null},"149":{"t":"grass","e":null}},"64":{"140":{"t":"grass","e":null},"141":{"t":"grass","e":null},"142":{"t":"grass","e":null},"143":{"t":"grass","e":null},"144":{"t":"grass","e":null},"145":{"t":"grass","e":null},"146":{"t":"grass","e":null},"147":{"t":"grass","e":null},"148":{"t":"grass","e":null},"149":{"t":"grass","e":null}},"65":{"140":{"t":"grass","e":null},"141":{"t":"grass","e":null},"142":{"t":"grass","e":null},"143":{"t":"grass","e":null},"144":{"t":"grass","e":null},"145":{"t":"grass","e":null},"146":{"t":"grass","e":null},"147":{"t":"grass","e":null},"148":{"t":"grass","e":null},"149":{"t":"grass","e":null}},"66":{"140":{"t":"grass","e":null},"141":{"t":"grass","e":null},"142":{"t":"grass","e":null},"143":{"t":"grass","e":null},"144":{"t":"grass","e":null},"145":{"t":"grass","e":null},"146":{"t":"grass","e":null},"147":{"t":"grass","e":null},"148":{"t":"grass","e":null},"149":{"t":"grass","e":null}},"67":{"140":{"t":"grass","e":null},"141":{"t":"grass","e":null},"142":{"t":"grass","e":null},"143":{"t":"grass","e":null},"144":{"t":"grass","e":null},"145":{"t":"grass","e":null},"146":{"t":"grass","e":null},"147":{"t":"grass","e":null},"148":{"t":"grass","e":null},"149":{"t":"grass","e":null}},"68":{"140":{"t":"water","e":null},"141":{"t":"grass","e":null},"142":{"t":"grass","e":null},"143":{"t":"grass","e":null},"144":{"t":"grass","e":null},"145":{"t":"grass","e":null},"146":{"t":"grass","e":null},"147":{"t":"grass","e":null},"148":{"t":"grass","e":null},"149":{"t":"grass","e":null}},"69":{"140":{"t":"water","e":null},"141":{"t":"grass","e":null},"142":{"t":"grass","e":null},"143":{"t":"grass","e":null},"144":{"t":"grass","e":null},"145":{"t":"grass","e":null},"146":{"t":"grass","e":null},"147":{"t":"grass","e":null},"148":{"t":"grass","e":null},"149":{"t":"grass","e":null}}}